lirc/__init__.py
lirc/client.py
lirc/connection/__init__.py
lirc/connection/abstract_connection.py
lirc/connection/default_connection.py
lirc/connection/lircd_connection.py
lirc/exceptions.py
lirc/reply_packet_parser.py
lirc-3.0.0.dist-info/LICENSE.rst
lirc-3.0.0.dist-info/METADATA
lirc-3.0.0.dist-info/WHEEL
lirc-3.0.0.dist-info/RECORD
