Metadata-Version: 2.1
Name: lirc
Version: 3.0.0
Summary: Interact with the daemon in the Linux Infrared Remote Control package
Home-page: https://github.com/eugenetriguba/lirc
License: MIT
Keywords: LIRC,IR
Author: Eugene Triguba
Author-email: eugenetriguba@gmail.com
Requires-Python: >=3.9,<4.0
Classifier: Development Status :: 5 - Production/Stable
Classifier: License :: OSI Approved :: MIT License
Classifier: Operating System :: MacOS
Classifier: Operating System :: Microsoft :: Windows
Classifier: Operating System :: POSIX :: Linux
Classifier: Programming Language :: Python :: 3
Classifier: Programming Language :: Python :: 3.9
Classifier: Programming Language :: Python :: 3.10
Classifier: Programming Language :: Python :: 3.11
Classifier: Programming Language :: Python :: 3.12
Classifier: Programming Language :: Python :: 3.13
Classifier: Topic :: Software Development :: Libraries :: Python Modules
Classifier: Topic :: System :: Hardware
Project-URL: Repository, https://github.com/eugenetriguba/lirc
